README.md
setup.cfg
setup.py
nomad_cbec_id_cli/__init__.py
nomad_cbec_id_cli/api_client.py
nomad_cbec_id_cli/configuration.py
nomad_cbec_id_cli/exceptions.py
nomad_cbec_id_cli/model_utils.py
nomad_cbec_id_cli/rest.py
nomad_cbec_id_cli.egg-info/PKG-INFO
nomad_cbec_id_cli.egg-info/SOURCES.txt
nomad_cbec_id_cli.egg-info/dependency_links.txt
nomad_cbec_id_cli.egg-info/requires.txt
nomad_cbec_id_cli.egg-info/top_level.txt
nomad_cbec_id_cli/api/__init__.py
nomad_cbec_id_cli/api/health_api.py
nomad_cbec_id_cli/api/user_api.py
nomad_cbec_id_cli/apis/__init__.py
nomad_cbec_id_cli/model/__init__.py
nomad_cbec_id_cli/model/api_response.py
nomad_cbec_id_cli/model/api_response_data.py
nomad_cbec_id_cli/models/__init__.py
test/test_api_response.py
test/test_api_response_data.py
test/test_health_api.py
test/test_user_api.py